sfdc_cli/__init__.py
sfdc_cli/anttools.py
sfdc_cli/apex.py
sfdc_cli/attachment.py
sfdc_cli/baseutil.py
sfdc_cli/browser.py
sfdc_cli/cli.py
sfdc_cli/codecreator.py
sfdc_cli/coder.py
sfdc_cli/const.py
sfdc_cli/data.py
sfdc_cli/folder.py
sfdc_cli/metadata.py
sfdc_cli/metadata_api.py
sfdc_cli/package_xml.py
sfdc_cli/permission.py
sfdc_cli/permission_util.py
sfdc_cli/project.py
sfdc_cli/rest_api.py
sfdc_cli/retrieve.py
sfdc_cli/setting.py
sfdc_cli/sobject.py
sfdc_cli/subconsole.py
sfdc_cli/template.py
sfdc_cli/tools.py
sfdc_cli/util.py
sfdc_cli/version.py
sfdc_cli/commands/__init__.py
sfdc_cli/commands/ant_migration_tool.py
sfdc_cli/commands/apex_execute.py
sfdc_cli/commands/apex_test_coverage.py
sfdc_cli/commands/apex_test_run.py
sfdc_cli/commands/call_rest_api.py
sfdc_cli/commands/coder_apex_page_generator.py
sfdc_cli/commands/coder_apex_snippet_insert_data_from_soql.py
sfdc_cli/commands/coder_apex_snippet_insert_ramdam_data.py
sfdc_cli/commands/coder_apex_testclass_generator.py
sfdc_cli/commands/coder_copy_aura.py
sfdc_cli/commands/coder_permission_build.py
sfdc_cli/commands/coder_permission_list.py
sfdc_cli/commands/coder_snippet_soql.py
sfdc_cli/commands/data_soql_query.py
sfdc_cli/commands/data_tooling_query.py
sfdc_cli/commands/download_attachment.py
sfdc_cli/commands/folder_list.py
sfdc_cli/commands/meta_attr.py
sfdc_cli/commands/meta_cache.py
sfdc_cli/commands/meta_delete.py
sfdc_cli/commands/meta_new.py
sfdc_cli/commands/meta_refresh.py
sfdc_cli/commands/meta_refresh_aura.py
sfdc_cli/commands/meta_refresh_dir.py
sfdc_cli/commands/meta_retrieve.py
sfdc_cli/commands/meta_template_apex.py
sfdc_cli/commands/meta_template_component.py
sfdc_cli/commands/meta_template_page.py
sfdc_cli/commands/meta_template_trigger.py
sfdc_cli/commands/meta_update.py
sfdc_cli/commands/packagexml_local.py
sfdc_cli/commands/packagexml_server.py
sfdc_cli/commands/project_init.py
sfdc_cli/commands/sobject_data_create.py
sfdc_cli/commands/sobject_data_delete.py
sfdc_cli-0.2.dist-info/LICENSE
sfdc_cli-0.2.dist-info/METADATA
sfdc_cli-0.2.dist-info/WHEEL
sfdc_cli-0.2.dist-info/entry_points.txt
sfdc_cli-0.2.dist-info/top_level.txt
sfdc_cli-0.2.dist-info/RECORD
