Metadata-Version: 2.1
Name: sfdc-cli
Version: 0.2
Summary: sfdc development kit
Home-page: https://github.com/exiahuang/sfdc-cli
Author: exiahuang
Author-email: exia.huang@outlook.com
License: Apache License 2.0
Keywords: sfdc-cli sdk tools xytools-cli salesforce
Platform: UNKNOWN
Classifier: Development Status :: 4 - Beta
Classifier: Intended Audience :: Developers
Classifier: License :: OSI Approved :: Apache Software License
Classifier: Natural Language :: English
Classifier: Operating System :: Unix
Classifier: Programming Language :: Python :: 3.2
Classifier: Programming Language :: Python :: 3.3
Classifier: Programming Language :: Python :: 3.4
Classifier: Programming Language :: Python :: 3.5
Classifier: Programming Language :: Python :: 3.6
Classifier: Programming Language :: Python :: 3.8
Classifier: Programming Language :: Python :: 3.8
Classifier: Programming Language :: Python :: Implementation :: PyPy
Classifier: Operating System :: OS Independent
Requires-Dist: requests[security]
Requires-Dist: cryptography (>=2.8)
Requires-Dist: XlsxWriter
Provides-Extra: tests
Requires-Dist: mock ; extra == 'tests'
Requires-Dist: nose ; extra == 'tests'
Requires-Dist: coverage ; extra == 'tests'
Requires-Dist: yanc ; extra == 'tests'
Requires-Dist: preggy ; extra == 'tests'
Requires-Dist: tox ; extra == 'tests'
Requires-Dist: ipdb ; extra == 'tests'
Requires-Dist: coveralls ; extra == 'tests'
Requires-Dist: sphinx ; extra == 'tests'
